README.md
setup.py
beepdrive/__init__.py
beepdrive/bdrive.py
beepdrive/pyside.py
beepdrive/snake.py
beepdrive/utils.py
beepdrive.egg-info/PKG-INFO
beepdrive.egg-info/SOURCES.txt
beepdrive.egg-info/dependency_links.txt
beepdrive.egg-info/entry_points.txt
beepdrive.egg-info/requires.txt
beepdrive.egg-info/top_level.txt
lib/Bd.png
lib/chromedriver_linux64
lib/chromedriver_mac64
lib/chromedriver_win32.exe