Metadata-Version: 2.1
Name: beepdrive
Version: 2019.3.27
Summary: Easily sync your PoliMi courses material locally.
Home-page: https://github.com/amecava/beepdrive
Author: Team 2 Quinti
Author-email: amedeo.cavallo96@gmail.com
License: UNKNOWN
Project-URL: Bug Reports, http://github.com/amecava/beepdrive/issues
Project-URL: Source, http://github.com/amecava/beepdrive
Keywords: sample setuptools development
Platform: UNKNOWN
Classifier: Development Status :: 3 - Alpha
Classifier: License :: OSI Approved :: MIT License
Classifier: Programming Language :: Python :: 3
Requires-Python: >=3.5
